{
    "dbc436f0e0": {
        "view://home@en_US": {
            "dev": "bf81bce448"
        },
        "component://force/lds@en_US": {
            "dev": "67bd332a20"
        },
        "view://mainLayout@en_US": {
            "dev": "67133358b1"
        },
        "view://preview@en_US": {
            "dev": "08a7bab2aa"
        },
        "component://c/lwcpopulatesessionobjectives@en_US": {
            "dev": "cad088fbbb"
        }
    },
    "de9ec49a26": {
        "view://home@en_US": {
            "dev": "bf81bce448"
        },
        "component://force/lds@en_US": {
            "dev": "67bd332a20"
        },
        "view://mainLayout@en_US": {
            "dev": "67133358b1"
        },
        "view://preview@en_US": {
            "dev": "08a7bab2aa"
        },
        "component://c/lwcpopulatesessionobjectives@en_US": {
            "dev": "fedb26a016"
        }
    },
    "844e7aa749": {
        "view://home@en_US": {
            "dev": "bf81bce448"
        },
        "component://force/lds@en_US": {
            "dev": "67bd332a20"
        },
        "view://mainLayout@en_US": {
            "dev": "67133358b1"
        },
        "view://preview@en_US": {
            "dev": "08a7bab2aa"
        },
        "component://c/lwcpopulatesessionobjectives@en_US": {
            "dev": "b4a15b6c54"
        }
    },
    "885332de38": {
        "view://home@en_US": {
            "dev": "bf81bce448"
        },
        "component://force/lds@en_US": {
            "dev": "67bd332a20"
        },
        "view://mainLayout@en_US": {
            "dev": "67133358b1"
        },
        "view://preview@en_US": {
            "dev": "08a7bab2aa"
        },
        "component://c/lwcpopulatesessionobjectives@en_US": {
            "dev": "7321c4c984"
        }
    }
}